{
  "m_GameObject": {
    "m_FileID": 0,
    "m_PathID": 0
  },
  "m_Enabled": 1,
  "m_Script": {
    "m_FileID": 0,
    "m_PathID": 8183613365264685828
  },
  "m_Name": "likabilityNINE_Main1_Hyakuichitaro_02",
  "_speakTranslationAssetAddress": "Translation/SpeakTranslationData/ActionSequence/LikabilityNINE/Main1/likabilityNINE_Main1_Hyakuichitaro",
  "AreaBehaviourBlackoutStart": 1,
  "AreaBehaviourMuteBgmStart": 0,
  "CommandData": [
    {
      "Enabled": 1,
      "Guid": "4b0be7d66241a49a08637e3e33538045",
      "Memo": "",
      "Command": "NineInitialize",
      "ParameterNames": [],
      "ParameterValues": []
    },
    {
      "Enabled": 1,
      "Guid": "11909a835ebf82542bf3ef3c909d71b8",
      "Memo": "トラッシュメンバー",
      "Command": "SectionBegin",
      "ParameterNames": [],
      "ParameterValues": []
    },
    {
      "Enabled": 1,
      "Guid": "fec2d12d258e57540b1e88a5f6af48f2",
      "Memo": "ツキ(1002)(8)",
      "Command": "NineAddUser",
      "ParameterNames": [
        "SpeakerId",
        "OverrideSpeakerName",
        "OverrideIconAssetPath"
      ],
      "ParameterValues": [
        "1002",
        "",
        ""
      ]
    },
    {
      "Enabled": 1,
      "Guid": "e2547b3dc69c714438ea660d8082f599",
      "Memo": "大井(1006)(46)",
      "Command": "NineAddUser",
      "ParameterNames": [
        "SpeakerId",
        "OverrideSpeakerName",
        "OverrideIconAssetPath"
      ],
      "ParameterValues": [
        "1006",
        "",
        ""
      ]
    },
    {
      "Enabled": 1,
      "Guid": "5f810cdde358d9345bc95f8a40cef8de",
      "Memo": "百一太郎(1007)(58)",
      "Command": "NineAddUser",
      "ParameterNames": [
        "SpeakerId",
        "OverrideSpeakerName",
        "OverrideIconAssetPath"
      ],
      "ParameterValues": [
        "1007",
        "",
        ""
      ]
    },
    {
      "Enabled": 1,
      "Guid": "94c5953986d3ef845b9a80f38f05b92f",
      "Memo": "五反田(1012)(44)",
      "Command": "NineAddUser",
      "ParameterNames": [
        "SpeakerId",
        "OverrideSpeakerName",
        "OverrideIconAssetPath"
      ],
      "ParameterValues": [
        "1012",
        "",
        ""
      ]
    },
    {
      "Enabled": 1,
      "Guid": "3ed18c5619acde5448147a08234cca59",
      "Memo": "",
      "Command": "SectionEnd",
      "ParameterNames": [],
      "ParameterValues": []
    },
    {
      "Enabled": 1,
      "Guid": "6a1512e5af0611043b3a621eef6c6f2c",
      "Memo": "",
      "Command": "NineMessage",
      "ParameterNames": [
        "WaitForTrigger",
        "WaitTriggerName",
        "InvokeTrigger",
        "InvokeTriggerName",
        "DelayMode",
        "DelaySec",
        "EnableTypingDurationOverride",
        "OverrideTypingDuration",
        "SpeakerId",
        "TextId",
        "Text",
        "MessageId",
        "HasAutoDelay",
        "TriggerMessageId"
      ],
      "ParameterValues": [
        "False",
        "",
        "False",
        "",
        "Auto",
        "0",
        "False",
        "1",
        "1012",
        "231344",
        "",
        "0",
        "True",
        "0"
      ]
    },
    {
      "Enabled": 1,
      "Guid": "5c2e687b6ed15d34ca08bc5ca2a6233f",
      "Memo": "",
      "Command": "NineMessage",
      "ParameterNames": [
        "WaitForTrigger",
        "WaitTriggerName",
        "InvokeTrigger",
        "InvokeTriggerName",
        "DelayMode",
        "DelaySec",
        "EnableTypingDurationOverride",
        "OverrideTypingDuration",
        "SpeakerId",
        "TextId",
        "Text",
        "MessageId",
        "HasAutoDelay",
        "TriggerMessageId"
      ],
      "ParameterValues": [
        "False",
        "",
        "False",
        "",
        "Manual",
        "0.6",
        "True",
        "1.4",
        "1002",
        "231345",
        "",
        "0",
        "True",
        "0"
      ]
    },
    {
      "Enabled": 1,
      "Guid": "896b52ac07a1b504c8c934ee714d8810",
      "Memo": "",
      "Command": "NineMessage",
      "ParameterNames": [
        "WaitForTrigger",
        "WaitTriggerName",
        "InvokeTrigger",
        "InvokeTriggerName",
        "DelayMode",
        "DelaySec",
        "EnableTypingDurationOverride",
        "OverrideTypingDuration",
        "SpeakerId",
        "TextId",
        "Text",
        "MessageId",
        "HasAutoDelay",
        "TriggerMessageId"
      ],
      "ParameterValues": [
        "False",
        "",
        "False",
        "",
        "Manual",
        "0.2",
        "True",
        "1.8",
        "1007",
        "231346",
        "",
        "0",
        "True",
        "0"
      ]
    },
    {
      "Enabled": 1,
      "Guid": "2afe9637be1e0724e97df6e6f93db0ce",
      "Memo": "",
      "Command": "NineMessage",
      "ParameterNames": [
        "WaitForTrigger",
        "WaitTriggerName",
        "InvokeTrigger",
        "InvokeTriggerName",
        "DelayMode",
        "DelaySec",
        "EnableTypingDurationOverride",
        "OverrideTypingDuration",
        "SpeakerId",
        "TextId",
        "Text",
        "MessageId",
        "HasAutoDelay",
        "TriggerMessageId"
      ],
      "ParameterValues": [
        "False",
        "",
        "False",
        "",
        "Manual",
        "0.3",
        "True",
        "1.8",
        "1012",
        "231347",
        "",
        "0",
        "True",
        "0"
      ]
    },
    {
      "Enabled": 1,
      "Guid": "7f14a14885e65964281dcee1945262b5",
      "Memo": "",
      "Command": "NineMessage",
      "ParameterNames": [
        "WaitForTrigger",
        "WaitTriggerName",
        "InvokeTrigger",
        "InvokeTriggerName",
        "DelayMode",
        "DelaySec",
        "EnableTypingDurationOverride",
        "OverrideTypingDuration",
        "SpeakerId",
        "TextId",
        "Text",
        "MessageId",
        "HasAutoDelay",
        "TriggerMessageId"
      ],
      "ParameterValues": [
        "False",
        "",
        "False",
        "",
        "Manual",
        "0.3",
        "True",
        "1",
        "1007",
        "231348",
        "",
        "0",
        "True",
        "0"
      ]
    },
    {
      "Enabled": 1,
      "Guid": "c2b8a18ffe4c585449211f386558fb43",
      "Memo": "",
      "Command": "NineMessage",
      "ParameterNames": [
        "WaitForTrigger",
        "WaitTriggerName",
        "InvokeTrigger",
        "InvokeTriggerName",
        "DelayMode",
        "DelaySec",
        "EnableTypingDurationOverride",
        "OverrideTypingDuration",
        "SpeakerId",
        "TextId",
        "Text",
        "MessageId",
        "HasAutoDelay",
        "TriggerMessageId"
      ],
      "ParameterValues": [
        "False",
        "",
        "False",
        "",
        "Manual",
        "0.2",
        "True",
        "1.7",
        "1007",
        "231349",
        "",
        "0",
        "True",
        "0"
      ]
    },
    {
      "Enabled": 1,
      "Guid": "f409c6c79e9b38f48bd6509f57c3b0f7",
      "Memo": "",
      "Command": "NineMessage",
      "ParameterNames": [
        "WaitForTrigger",
        "WaitTriggerName",
        "InvokeTrigger",
        "InvokeTriggerName",
        "DelayMode",
        "DelaySec",
        "EnableTypingDurationOverride",
        "OverrideTypingDuration",
        "SpeakerId",
        "TextId",
        "Text",
        "MessageId",
        "HasAutoDelay",
        "TriggerMessageId"
      ],
      "ParameterValues": [
        "False",
        "",
        "False",
        "",
        "Manual",
        "0.3",
        "True",
        "1.7",
        "1007",
        "231350",
        "",
        "0",
        "True",
        "0"
      ]
    },
    {
      "Enabled": 1,
      "Guid": "f66495c01a5077e47919a11c5098fac3",
      "Memo": "",
      "Command": "NineMessage",
      "ParameterNames": [
        "WaitForTrigger",
        "WaitTriggerName",
        "InvokeTrigger",
        "InvokeTriggerName",
        "DelayMode",
        "DelaySec",
        "EnableTypingDurationOverride",
        "OverrideTypingDuration",
        "SpeakerId",
        "TextId",
        "Text",
        "MessageId",
        "HasAutoDelay",
        "TriggerMessageId"
      ],
      "ParameterValues": [
        "False",
        "",
        "False",
        "",
        "Manual",
        "0.3",
        "True",
        "2.3",
        "1006",
        "231351",
        "",
        "0",
        "True",
        "0"
      ]
    },
    {
      "Enabled": 1,
      "Guid": "5b1ddb1b7f1fc3249b05e765507f8635",
      "Memo": "",
      "Command": "NineMessage",
      "ParameterNames": [
        "WaitForTrigger",
        "WaitTriggerName",
        "InvokeTrigger",
        "InvokeTriggerName",
        "DelayMode",
        "DelaySec",
        "EnableTypingDurationOverride",
        "OverrideTypingDuration",
        "SpeakerId",
        "TextId",
        "Text",
        "MessageId",
        "HasAutoDelay",
        "TriggerMessageId"
      ],
      "ParameterValues": [
        "False",
        "",
        "False",
        "",
        "Manual",
        "0.4",
        "True",
        "1.1",
        "1006",
        "231352",
        "",
        "0",
        "True",
        "0"
      ]
    },
    {
      "Enabled": 1,
      "Guid": "fd8c3a734693feb4eb7733fb8e3114d2",
      "Memo": "",
      "Command": "NineMessage",
      "ParameterNames": [
        "WaitForTrigger",
        "WaitTriggerName",
        "InvokeTrigger",
        "InvokeTriggerName",
        "DelayMode",
        "DelaySec",
        "EnableTypingDurationOverride",
        "OverrideTypingDuration",
        "SpeakerId",
        "TextId",
        "Text",
        "MessageId",
        "HasAutoDelay",
        "TriggerMessageId"
      ],
      "ParameterValues": [
        "False",
        "",
        "False",
        "",
        "Manual",
        "0.3",
        "True",
        "1",
        "1002",
        "231353",
        "",
        "0",
        "True",
        "0"
      ]
    },
    {
      "Enabled": 1,
      "Guid": "7f97651e79a009e408a5e52f4739b920",
      "Memo": "",
      "Command": "NineMessage",
      "ParameterNames": [
        "WaitForTrigger",
        "WaitTriggerName",
        "InvokeTrigger",
        "InvokeTriggerName",
        "DelayMode",
        "DelaySec",
        "EnableTypingDurationOverride",
        "OverrideTypingDuration",
        "SpeakerId",
        "TextId",
        "Text",
        "MessageId",
        "HasAutoDelay",
        "TriggerMessageId"
      ],
      "ParameterValues": [
        "False",
        "",
        "False",
        "",
        "Manual",
        "0.2",
        "True",
        "1.7",
        "1002",
        "231354",
        "",
        "0",
        "True",
        "0"
      ]
    },
    {
      "Enabled": 1,
      "Guid": "2632e6160b4718a43a6813a217502675",
      "Memo": "",
      "Command": "NineMessage",
      "ParameterNames": [
        "WaitForTrigger",
        "WaitTriggerName",
        "InvokeTrigger",
        "InvokeTriggerName",
        "DelayMode",
        "DelaySec",
        "EnableTypingDurationOverride",
        "OverrideTypingDuration",
        "SpeakerId",
        "TextId",
        "Text",
        "MessageId",
        "HasAutoDelay",
        "TriggerMessageId"
      ],
      "ParameterValues": [
        "False",
        "",
        "False",
        "",
        "Manual",
        "0.3",
        "True",
        "1.6",
        "1002",
        "231355",
        "",
        "0",
        "True",
        "0"
      ]
    },
    {
      "Enabled": 1,
      "Guid": "c22ce1074f1ae0247b531a959823fdee",
      "Memo": "",
      "Command": "NineMessage",
      "ParameterNames": [
        "WaitForTrigger",
        "WaitTriggerName",
        "InvokeTrigger",
        "InvokeTriggerName",
        "DelayMode",
        "DelaySec",
        "EnableTypingDurationOverride",
        "OverrideTypingDuration",
        "SpeakerId",
        "TextId",
        "Text",
        "MessageId",
        "HasAutoDelay",
        "TriggerMessageId"
      ],
      "ParameterValues": [
        "False",
        "",
        "False",
        "",
        "Manual",
        "0.2",
        "True",
        "1.3",
        "1007",
        "231356",
        "",
        "0",
        "True",
        "0"
      ]
    },
    {
      "Enabled": 1,
      "Guid": "173e1abb267c8ce4d9050ce0ba17c2ad",
      "Memo": "",
      "Command": "NineMessage",
      "ParameterNames": [
        "WaitForTrigger",
        "WaitTriggerName",
        "InvokeTrigger",
        "InvokeTriggerName",
        "DelayMode",
        "DelaySec",
        "EnableTypingDurationOverride",
        "OverrideTypingDuration",
        "SpeakerId",
        "TextId",
        "Text",
        "MessageId",
        "HasAutoDelay",
        "TriggerMessageId"
      ],
      "ParameterValues": [
        "False",
        "",
        "False",
        "",
        "Manual",
        "0.2",
        "True",
        "1.8",
        "1007",
        "231357",
        "",
        "0",
        "True",
        "0"
      ]
    },
    {
      "Enabled": 1,
      "Guid": "5bb3fff7a4a7dd440b3d906f0424f94d",
      "Memo": "",
      "Command": "NineMessage",
      "ParameterNames": [
        "WaitForTrigger",
        "WaitTriggerName",
        "InvokeTrigger",
        "InvokeTriggerName",
        "DelayMode",
        "DelaySec",
        "EnableTypingDurationOverride",
        "OverrideTypingDuration",
        "SpeakerId",
        "TextId",
        "Text",
        "MessageId",
        "HasAutoDelay",
        "TriggerMessageId"
      ],
      "ParameterValues": [
        "False",
        "",
        "False",
        "",
        "Manual",
        "0.3",
        "True",
        "1.3",
        "1007",
        "231358",
        "",
        "0",
        "True",
        "0"
      ]
    },
    {
      "Enabled": 1,
      "Guid": "042c689bed29bc941a0799da355939c7",
      "Memo": "",
      "Command": "NineMessage",
      "ParameterNames": [
        "WaitForTrigger",
        "WaitTriggerName",
        "InvokeTrigger",
        "InvokeTriggerName",
        "DelayMode",
        "DelaySec",
        "EnableTypingDurationOverride",
        "OverrideTypingDuration",
        "SpeakerId",
        "TextId",
        "Text",
        "MessageId",
        "HasAutoDelay",
        "TriggerMessageId"
      ],
      "ParameterValues": [
        "False",
        "",
        "False",
        "",
        "Manual",
        "0.2",
        "True",
        "1.4",
        "1002",
        "231359",
        "",
        "0",
        "True",
        "0"
      ]
    },
    {
      "Enabled": 1,
      "Guid": "809ac9d21b885b3488cbf43d829214d4",
      "Memo": "",
      "Command": "NineMessage",
      "ParameterNames": [
        "WaitForTrigger",
        "WaitTriggerName",
        "InvokeTrigger",
        "InvokeTriggerName",
        "DelayMode",
        "DelaySec",
        "EnableTypingDurationOverride",
        "OverrideTypingDuration",
        "SpeakerId",
        "TextId",
        "Text",
        "MessageId",
        "HasAutoDelay",
        "TriggerMessageId"
      ],
      "ParameterValues": [
        "False",
        "",
        "False",
        "",
        "Manual",
        "0.3",
        "True",
        "1.5",
        "1006",
        "231360",
        "",
        "0",
        "True",
        "0"
      ]
    },
    {
      "Enabled": 1,
      "Guid": "45bfd5e7905a70e49ba417fb113e8530",
      "Memo": "",
      "Command": "NineMessage",
      "ParameterNames": [
        "WaitForTrigger",
        "WaitTriggerName",
        "InvokeTrigger",
        "InvokeTriggerName",
        "DelayMode",
        "DelaySec",
        "EnableTypingDurationOverride",
        "OverrideTypingDuration",
        "SpeakerId",
        "TextId",
        "Text",
        "MessageId",
        "HasAutoDelay",
        "TriggerMessageId"
      ],
      "ParameterValues": [
        "False",
        "",
        "False",
        "",
        "Manual",
        "0.3",
        "True",
        "1.8",
        "1012",
        "231361",
        "",
        "0",
        "True",
        "0"
      ]
    },
    {
      "Enabled": 1,
      "Guid": "3e40c71cf7608e34c86c5262053b1bba",
      "Memo": "",
      "Command": "NineMessage",
      "ParameterNames": [
        "WaitForTrigger",
        "WaitTriggerName",
        "InvokeTrigger",
        "InvokeTriggerName",
        "DelayMode",
        "DelaySec",
        "EnableTypingDurationOverride",
        "OverrideTypingDuration",
        "SpeakerId",
        "TextId",
        "Text",
        "MessageId",
        "HasAutoDelay",
        "TriggerMessageId"
      ],
      "ParameterValues": [
        "False",
        "",
        "False",
        "",
        "Manual",
        "0.4",
        "True",
        "1.6",
        "1012",
        "231362",
        "",
        "0",
        "True",
        "0"
      ]
    },
    {
      "Enabled": 1,
      "Guid": "2eba474149e90bc4abeb0ff7b99ea724",
      "Memo": "",
      "Command": "NineMessage",
      "ParameterNames": [
        "WaitForTrigger",
        "WaitTriggerName",
        "InvokeTrigger",
        "InvokeTriggerName",
        "DelayMode",
        "DelaySec",
        "EnableTypingDurationOverride",
        "OverrideTypingDuration",
        "SpeakerId",
        "TextId",
        "Text",
        "MessageId",
        "HasAutoDelay",
        "TriggerMessageId"
      ],
      "ParameterValues": [
        "False",
        "",
        "False",
        "",
        "Manual",
        "0.3",
        "True",
        "2.3",
        "1007",
        "231363",
        "",
        "0",
        "True",
        "0"
      ]
    },
    {
      "Enabled": 1,
      "Guid": "314833fbf0b739a4abd62b06dfe4dc64",
      "Memo": "",
      "Command": "NineMessage",
      "ParameterNames": [
        "WaitForTrigger",
        "WaitTriggerName",
        "InvokeTrigger",
        "InvokeTriggerName",
        "DelayMode",
        "DelaySec",
        "EnableTypingDurationOverride",
        "OverrideTypingDuration",
        "SpeakerId",
        "TextId",
        "Text",
        "MessageId",
        "HasAutoDelay",
        "TriggerMessageId"
      ],
      "ParameterValues": [
        "False",
        "",
        "False",
        "",
        "Manual",
        "0.3",
        "True",
        "1",
        "1007",
        "231364",
        "",
        "0",
        "True",
        "0"
      ]
    },
    {
      "Enabled": 1,
      "Guid": "b68b4cf79acb55749911ea441963e780",
      "Memo": "",
      "Command": "Wait",
      "ParameterNames": [
        "DurationSec"
      ],
      "ParameterValues": [
        "2"
      ]
    },
    {
      "Enabled": 1,
      "Guid": "f38100c052ffb794b9767da668b1c845",
      "Memo": "",
      "Command": "NineComplete",
      "ParameterNames": [],
      "ParameterValues": []
    }
  ]
}