{
  "m_GameObject": {
    "m_FileID": 0,
    "m_PathID": 0
  },
  "m_Enabled": 1,
  "m_Script": {
    "m_FileID": 0,
    "m_PathID": 8183613365264685828
  },
  "m_Name": "likabilityNINE_common_Todoroki_04",
  "_speakTranslationAssetAddress": "Translation/SpeakTranslationData/ActionSequence/LikabilityNINE/common/likabilityNINE_common_Todoroki",
  "AreaBehaviourBlackoutStart": 1,
  "AreaBehaviourMuteBgmStart": 0,
  "CommandData": [
    {
      "Enabled": 1,
      "Guid": "4b0be7d66241a49a08637e3e33538045",
      "Memo": "",
      "Command": "NineInitialize",
      "ParameterNames": [],
      "ParameterValues": []
    },
    {
      "Enabled": 1,
      "Guid": "aae4bed21eea5744f8489c13a3b2ed1b",
      "Memo": "トラッシュメンバー",
      "Command": "SectionBegin",
      "ParameterNames": [],
      "ParameterValues": []
    },
    {
      "Enabled": 1,
      "Guid": "c2e3767e32639ca45b84494f79fbd9de",
      "Memo": "ツキ",
      "Command": "NineAddUser",
      "ParameterNames": [
        "SpeakerId",
        "OverrideSpeakerName",
        "OverrideIconAssetPath"
      ],
      "ParameterValues": [
        "1002",
        "",
        ""
      ]
    },
    {
      "Enabled": 1,
      "Guid": "4022b8455e3dc3b41b1cbb81a6ddaaf3",
      "Memo": "ジオウ",
      "Command": "NineAddUser",
      "ParameterNames": [
        "SpeakerId",
        "OverrideSpeakerName",
        "OverrideIconAssetPath"
      ],
      "ParameterValues": [
        "1003",
        "",
        ""
      ]
    },
    {
      "Enabled": 1,
      "Guid": "82bab97644c75f24485c3542926d4368",
      "Memo": "ミウ",
      "Command": "NineAddUser",
      "ParameterNames": [
        "SpeakerId",
        "OverrideSpeakerName",
        "OverrideIconAssetPath"
      ],
      "ParameterValues": [
        "1004",
        "",
        ""
      ]
    },
    {
      "Enabled": 1,
      "Guid": "a2ad16bafa26f06478cd5cf424ba7363",
      "Memo": "轟",
      "Command": "NineAddUser",
      "ParameterNames": [
        "SpeakerId",
        "OverrideSpeakerName",
        "OverrideIconAssetPath"
      ],
      "ParameterValues": [
        "1009",
        "",
        ""
      ]
    },
    {
      "Enabled": 1,
      "Guid": "ab661b4b3d922e347a3dff7d80888e4d",
      "Memo": "",
      "Command": "SectionEnd",
      "ParameterNames": [],
      "ParameterValues": []
    },
    {
      "Enabled": 1,
      "Guid": "6a1512e5af0611043b3a621eef6c6f2c",
      "Memo": "",
      "Command": "NineMessage",
      "ParameterNames": [
        "WaitForTrigger",
        "WaitTriggerName",
        "InvokeTrigger",
        "InvokeTriggerName",
        "DelayMode",
        "DelaySec",
        "EnableTypingDurationOverride",
        "OverrideTypingDuration",
        "SpeakerId",
        "TextId",
        "Text",
        "MessageId",
        "HasAutoDelay",
        "TriggerMessageId"
      ],
      "ParameterValues": [
        "False",
        "",
        "False",
        "",
        "Auto",
        "0",
        "True",
        "3.1",
        "1002",
        "242024",
        "",
        "0",
        "True",
        "0"
      ]
    },
    {
      "Enabled": 1,
      "Guid": "1770ca1f64882d847940c6b95e27b7f5",
      "Memo": "",
      "Command": "NineMessage",
      "ParameterNames": [
        "WaitForTrigger",
        "WaitTriggerName",
        "InvokeTrigger",
        "InvokeTriggerName",
        "DelayMode",
        "DelaySec",
        "EnableTypingDurationOverride",
        "OverrideTypingDuration",
        "SpeakerId",
        "TextId",
        "Text",
        "MessageId",
        "HasAutoDelay",
        "TriggerMessageId"
      ],
      "ParameterValues": [
        "False",
        "",
        "False",
        "",
        "Manual",
        "0.7",
        "True",
        "1.7",
        "1002",
        "242025",
        "",
        "0",
        "True",
        "0"
      ]
    },
    {
      "Enabled": 1,
      "Guid": "205f03c864e34824a8948b9294e44983",
      "Memo": "",
      "Command": "NineMessage",
      "ParameterNames": [
        "WaitForTrigger",
        "WaitTriggerName",
        "InvokeTrigger",
        "InvokeTriggerName",
        "DelayMode",
        "DelaySec",
        "EnableTypingDurationOverride",
        "OverrideTypingDuration",
        "SpeakerId",
        "TextId",
        "Text",
        "MessageId",
        "HasAutoDelay",
        "TriggerMessageId"
      ],
      "ParameterValues": [
        "False",
        "",
        "False",
        "",
        "Manual",
        "0.3",
        "True",
        "1.5",
        "1002",
        "242026",
        "",
        "0",
        "True",
        "0"
      ]
    },
    {
      "Enabled": 1,
      "Guid": "0785833c8993f0741a7325001cfc3b4e",
      "Memo": "",
      "Command": "NinePicture",
      "ParameterNames": [
        "WaitForTrigger",
        "WaitTriggerName",
        "InvokeTrigger",
        "InvokeTriggerName",
        "DelayMode",
        "DelaySec",
        "EnableTypingDurationOverride",
        "OverrideTypingDuration",
        "SpeakerId",
        "TranslationSpeakerId",
        "PictureId",
        "MessageId",
        "HasAutoDelay",
        "TriggerMessageId"
      ],
      "ParameterValues": [
        "False",
        "",
        "False",
        "",
        "Manual",
        "0.7",
        "True",
        "0",
        "1002",
        "8",
        "feb599a3c16c1470b985e86faa7aa2f7",
        "0",
        "True",
        "0"
      ]
    },
    {
      "Enabled": 1,
      "Guid": "fb7fdb7a6bf4d434b963fdde543b625a",
      "Memo": "",
      "Command": "NineMessage",
      "ParameterNames": [
        "WaitForTrigger",
        "WaitTriggerName",
        "InvokeTrigger",
        "InvokeTriggerName",
        "DelayMode",
        "DelaySec",
        "EnableTypingDurationOverride",
        "OverrideTypingDuration",
        "SpeakerId",
        "TextId",
        "Text",
        "MessageId",
        "HasAutoDelay",
        "TriggerMessageId"
      ],
      "ParameterValues": [
        "False",
        "",
        "False",
        "",
        "Manual",
        "1",
        "True",
        "2.2",
        "1009",
        "242028",
        "",
        "0",
        "True",
        "0"
      ]
    },
    {
      "Enabled": 1,
      "Guid": "4ba6ed65c071ac343bd488b9f1a9a02e",
      "Memo": "",
      "Command": "NineMessage",
      "ParameterNames": [
        "WaitForTrigger",
        "WaitTriggerName",
        "InvokeTrigger",
        "InvokeTriggerName",
        "DelayMode",
        "DelaySec",
        "EnableTypingDurationOverride",
        "OverrideTypingDuration",
        "SpeakerId",
        "TextId",
        "Text",
        "MessageId",
        "HasAutoDelay",
        "TriggerMessageId"
      ],
      "ParameterValues": [
        "False",
        "",
        "False",
        "",
        "Manual",
        "0.3",
        "True",
        "1.1",
        "1002",
        "242029",
        "",
        "0",
        "True",
        "0"
      ]
    },
    {
      "Enabled": 1,
      "Guid": "0db07d4fc57fc134a93ef679b4a14f4e",
      "Memo": "",
      "Command": "NineMessage",
      "ParameterNames": [
        "WaitForTrigger",
        "WaitTriggerName",
        "InvokeTrigger",
        "InvokeTriggerName",
        "DelayMode",
        "DelaySec",
        "EnableTypingDurationOverride",
        "OverrideTypingDuration",
        "SpeakerId",
        "TextId",
        "Text",
        "MessageId",
        "HasAutoDelay",
        "TriggerMessageId"
      ],
      "ParameterValues": [
        "False",
        "",
        "False",
        "",
        "Manual",
        "0.3",
        "True",
        "2.3",
        "1002",
        "242030",
        "",
        "0",
        "True",
        "0"
      ]
    },
    {
      "Enabled": 1,
      "Guid": "854012076b4c0fd4aa608e3bb219d27c",
      "Memo": "",
      "Command": "NineMessage",
      "ParameterNames": [
        "WaitForTrigger",
        "WaitTriggerName",
        "InvokeTrigger",
        "InvokeTriggerName",
        "DelayMode",
        "DelaySec",
        "EnableTypingDurationOverride",
        "OverrideTypingDuration",
        "SpeakerId",
        "TextId",
        "Text",
        "MessageId",
        "HasAutoDelay",
        "TriggerMessageId"
      ],
      "ParameterValues": [
        "False",
        "",
        "False",
        "",
        "Manual",
        "0.4",
        "True",
        "1.7",
        "1002",
        "242031",
        "",
        "0",
        "True",
        "0"
      ]
    },
    {
      "Enabled": 1,
      "Guid": "f9bd3130cc45d774d8896a82e595bf9c",
      "Memo": "",
      "Command": "NineMessage",
      "ParameterNames": [
        "WaitForTrigger",
        "WaitTriggerName",
        "InvokeTrigger",
        "InvokeTriggerName",
        "DelayMode",
        "DelaySec",
        "EnableTypingDurationOverride",
        "OverrideTypingDuration",
        "SpeakerId",
        "TextId",
        "Text",
        "MessageId",
        "HasAutoDelay",
        "TriggerMessageId"
      ],
      "ParameterValues": [
        "False",
        "",
        "False",
        "",
        "Manual",
        "0.3",
        "True",
        "1.8",
        "1009",
        "242032",
        "",
        "0",
        "True",
        "0"
      ]
    },
    {
      "Enabled": 1,
      "Guid": "5643258d2a52f1b43a8590c946d41608",
      "Memo": "",
      "Command": "NineMessage",
      "ParameterNames": [
        "WaitForTrigger",
        "WaitTriggerName",
        "InvokeTrigger",
        "InvokeTriggerName",
        "DelayMode",
        "DelaySec",
        "EnableTypingDurationOverride",
        "OverrideTypingDuration",
        "SpeakerId",
        "TextId",
        "Text",
        "MessageId",
        "HasAutoDelay",
        "TriggerMessageId"
      ],
      "ParameterValues": [
        "False",
        "",
        "False",
        "",
        "Manual",
        "0.3",
        "True",
        "2.2",
        "1009",
        "242033",
        "",
        "0",
        "True",
        "0"
      ]
    },
    {
      "Enabled": 1,
      "Guid": "61d67817771a38b4cbe17772de10f04e",
      "Memo": "",
      "Command": "NineMessage",
      "ParameterNames": [
        "WaitForTrigger",
        "WaitTriggerName",
        "InvokeTrigger",
        "InvokeTriggerName",
        "DelayMode",
        "DelaySec",
        "EnableTypingDurationOverride",
        "OverrideTypingDuration",
        "SpeakerId",
        "TextId",
        "Text",
        "MessageId",
        "HasAutoDelay",
        "TriggerMessageId"
      ],
      "ParameterValues": [
        "False",
        "",
        "False",
        "",
        "Manual",
        "0.3",
        "True",
        "2.6",
        "1009",
        "242034",
        "",
        "0",
        "True",
        "0"
      ]
    },
    {
      "Enabled": 1,
      "Guid": "4d01e26fac514cf46afacc99100c4fa5",
      "Memo": "",
      "Command": "NineMessage",
      "ParameterNames": [
        "WaitForTrigger",
        "WaitTriggerName",
        "InvokeTrigger",
        "InvokeTriggerName",
        "DelayMode",
        "DelaySec",
        "EnableTypingDurationOverride",
        "OverrideTypingDuration",
        "SpeakerId",
        "TextId",
        "Text",
        "MessageId",
        "HasAutoDelay",
        "TriggerMessageId"
      ],
      "ParameterValues": [
        "False",
        "",
        "False",
        "",
        "Manual",
        "0.4",
        "True",
        "1.8",
        "1003",
        "242035",
        "",
        "0",
        "True",
        "0"
      ]
    },
    {
      "Enabled": 1,
      "Guid": "eba79e4dfcb82ed4fa5b0a7a37f7a286",
      "Memo": "",
      "Command": "NineMessage",
      "ParameterNames": [
        "WaitForTrigger",
        "WaitTriggerName",
        "InvokeTrigger",
        "InvokeTriggerName",
        "DelayMode",
        "DelaySec",
        "EnableTypingDurationOverride",
        "OverrideTypingDuration",
        "SpeakerId",
        "TextId",
        "Text",
        "MessageId",
        "HasAutoDelay",
        "TriggerMessageId"
      ],
      "ParameterValues": [
        "False",
        "",
        "False",
        "",
        "Manual",
        "0.3",
        "True",
        "1.5",
        "1003",
        "242036",
        "",
        "0",
        "True",
        "0"
      ]
    },
    {
      "Enabled": 1,
      "Guid": "174eb0cb9b908d0409d2621d264cd0b3",
      "Memo": "",
      "Command": "NineMessage",
      "ParameterNames": [
        "WaitForTrigger",
        "WaitTriggerName",
        "InvokeTrigger",
        "InvokeTriggerName",
        "DelayMode",
        "DelaySec",
        "EnableTypingDurationOverride",
        "OverrideTypingDuration",
        "SpeakerId",
        "TextId",
        "Text",
        "MessageId",
        "HasAutoDelay",
        "TriggerMessageId"
      ],
      "ParameterValues": [
        "False",
        "",
        "False",
        "",
        "Manual",
        "0.3",
        "True",
        "1.5",
        "1009",
        "242037",
        "",
        "0",
        "True",
        "0"
      ]
    },
    {
      "Enabled": 1,
      "Guid": "a793d1bc2ed020a4ebf8117eb2325e0b",
      "Memo": "",
      "Command": "NineMessage",
      "ParameterNames": [
        "WaitForTrigger",
        "WaitTriggerName",
        "InvokeTrigger",
        "InvokeTriggerName",
        "DelayMode",
        "DelaySec",
        "EnableTypingDurationOverride",
        "OverrideTypingDuration",
        "SpeakerId",
        "TextId",
        "Text",
        "MessageId",
        "HasAutoDelay",
        "TriggerMessageId"
      ],
      "ParameterValues": [
        "False",
        "",
        "False",
        "",
        "Manual",
        "0.5",
        "True",
        "1.9",
        "1009",
        "242038",
        "",
        "0",
        "True",
        "0"
      ]
    },
    {
      "Enabled": 1,
      "Guid": "ad9cc81d939243741b24eaff6e724ed3",
      "Memo": "",
      "Command": "NineMessage",
      "ParameterNames": [
        "WaitForTrigger",
        "WaitTriggerName",
        "InvokeTrigger",
        "InvokeTriggerName",
        "DelayMode",
        "DelaySec",
        "EnableTypingDurationOverride",
        "OverrideTypingDuration",
        "SpeakerId",
        "TextId",
        "Text",
        "MessageId",
        "HasAutoDelay",
        "TriggerMessageId"
      ],
      "ParameterValues": [
        "False",
        "",
        "False",
        "",
        "Manual",
        "0.2",
        "True",
        "2",
        "1009",
        "242039",
        "",
        "0",
        "True",
        "0"
      ]
    },
    {
      "Enabled": 1,
      "Guid": "73ffc8bb74936f24198e7693cbdbdb98",
      "Memo": "",
      "Command": "NineMessage",
      "ParameterNames": [
        "WaitForTrigger",
        "WaitTriggerName",
        "InvokeTrigger",
        "InvokeTriggerName",
        "DelayMode",
        "DelaySec",
        "EnableTypingDurationOverride",
        "OverrideTypingDuration",
        "SpeakerId",
        "TextId",
        "Text",
        "MessageId",
        "HasAutoDelay",
        "TriggerMessageId"
      ],
      "ParameterValues": [
        "False",
        "",
        "False",
        "",
        "Manual",
        "0.7",
        "True",
        "1.9",
        "1002",
        "242040",
        "",
        "0",
        "True",
        "0"
      ]
    },
    {
      "Enabled": 1,
      "Guid": "90577f324f7692b47b6c6be4645f630b",
      "Memo": "",
      "Command": "NineMessage",
      "ParameterNames": [
        "WaitForTrigger",
        "WaitTriggerName",
        "InvokeTrigger",
        "InvokeTriggerName",
        "DelayMode",
        "DelaySec",
        "EnableTypingDurationOverride",
        "OverrideTypingDuration",
        "SpeakerId",
        "TextId",
        "Text",
        "MessageId",
        "HasAutoDelay",
        "TriggerMessageId"
      ],
      "ParameterValues": [
        "False",
        "",
        "False",
        "",
        "Manual",
        "0.7",
        "True",
        "2.1",
        "1004",
        "242041",
        "",
        "0",
        "True",
        "0"
      ]
    },
    {
      "Enabled": 1,
      "Guid": "47a913f62da6b0d49ace4f8d2c353a56",
      "Memo": "",
      "Command": "NineMessage",
      "ParameterNames": [
        "WaitForTrigger",
        "WaitTriggerName",
        "InvokeTrigger",
        "InvokeTriggerName",
        "DelayMode",
        "DelaySec",
        "EnableTypingDurationOverride",
        "OverrideTypingDuration",
        "SpeakerId",
        "TextId",
        "Text",
        "MessageId",
        "HasAutoDelay",
        "TriggerMessageId"
      ],
      "ParameterValues": [
        "False",
        "",
        "False",
        "",
        "Manual",
        "0.4",
        "True",
        "1.5",
        "1004",
        "242042",
        "",
        "0",
        "True",
        "0"
      ]
    },
    {
      "Enabled": 1,
      "Guid": "8a86f03f1acd067428cf0eacfa86b967",
      "Memo": "",
      "Command": "NineMessage",
      "ParameterNames": [
        "WaitForTrigger",
        "WaitTriggerName",
        "InvokeTrigger",
        "InvokeTriggerName",
        "DelayMode",
        "DelaySec",
        "EnableTypingDurationOverride",
        "OverrideTypingDuration",
        "SpeakerId",
        "TextId",
        "Text",
        "MessageId",
        "HasAutoDelay",
        "TriggerMessageId"
      ],
      "ParameterValues": [
        "False",
        "",
        "False",
        "",
        "Manual",
        "0.3",
        "True",
        "1.5",
        "1004",
        "242043",
        "",
        "0",
        "True",
        "0"
      ]
    },
    {
      "Enabled": 1,
      "Guid": "f846dd2c508bd1540b80c1103d8bff62",
      "Memo": "",
      "Command": "NineMessage",
      "ParameterNames": [
        "WaitForTrigger",
        "WaitTriggerName",
        "InvokeTrigger",
        "InvokeTriggerName",
        "DelayMode",
        "DelaySec",
        "EnableTypingDurationOverride",
        "OverrideTypingDuration",
        "SpeakerId",
        "TextId",
        "Text",
        "MessageId",
        "HasAutoDelay",
        "TriggerMessageId"
      ],
      "ParameterValues": [
        "False",
        "",
        "False",
        "",
        "Manual",
        "0.3",
        "True",
        "2.2",
        "1009",
        "242044",
        "",
        "0",
        "True",
        "0"
      ]
    },
    {
      "Enabled": 1,
      "Guid": "dd44aab054e63904eb0056f81a4196d1",
      "Memo": "",
      "Command": "NineMessage",
      "ParameterNames": [
        "WaitForTrigger",
        "WaitTriggerName",
        "InvokeTrigger",
        "InvokeTriggerName",
        "DelayMode",
        "DelaySec",
        "EnableTypingDurationOverride",
        "OverrideTypingDuration",
        "SpeakerId",
        "TextId",
        "Text",
        "MessageId",
        "HasAutoDelay",
        "TriggerMessageId"
      ],
      "ParameterValues": [
        "False",
        "",
        "False",
        "",
        "Manual",
        "0.7",
        "True",
        "2.2",
        "1009",
        "242045",
        "",
        "0",
        "True",
        "0"
      ]
    },
    {
      "Enabled": 1,
      "Guid": "e82b679bbd0c5f945a0ba2ba63f611a5",
      "Memo": "",
      "Command": "NineMessage",
      "ParameterNames": [
        "WaitForTrigger",
        "WaitTriggerName",
        "InvokeTrigger",
        "InvokeTriggerName",
        "DelayMode",
        "DelaySec",
        "EnableTypingDurationOverride",
        "OverrideTypingDuration",
        "SpeakerId",
        "TextId",
        "Text",
        "MessageId",
        "HasAutoDelay",
        "TriggerMessageId"
      ],
      "ParameterValues": [
        "False",
        "",
        "False",
        "",
        "Manual",
        "0.3",
        "True",
        "2.7",
        "1009",
        "242046",
        "",
        "0",
        "True",
        "0"
      ]
    },
    {
      "Enabled": 1,
      "Guid": "663129e8cdad24d45b407fa8da411d10",
      "Memo": "",
      "Command": "Wait",
      "ParameterNames": [
        "DurationSec"
      ],
      "ParameterValues": [
        "2"
      ]
    },
    {
      "Enabled": 1,
      "Guid": "5a9b5234adbb729499478f06f6b5c586",
      "Memo": "",
      "Command": "NineComplete",
      "ParameterNames": [],
      "ParameterValues": []
    }
  ]
}